alibabacloud_bailian20231229/__init__.py
alibabacloud_bailian20231229/client.py
alibabacloud_bailian20231229/models/__init__.py
alibabacloud_bailian20231229/models/_add_category_request.py
alibabacloud_bailian20231229/models/_add_category_response.py
alibabacloud_bailian20231229/models/_add_category_response_body.py
alibabacloud_bailian20231229/models/_add_file_request.py
alibabacloud_bailian20231229/models/_add_file_response.py
alibabacloud_bailian20231229/models/_add_file_response_body.py
alibabacloud_bailian20231229/models/_add_file_shrink_request.py
alibabacloud_bailian20231229/models/_add_files_from_authorized_oss_request.py
alibabacloud_bailian20231229/models/_add_files_from_authorized_oss_response.py
alibabacloud_bailian20231229/models/_add_files_from_authorized_oss_response_body.py
alibabacloud_bailian20231229/models/_add_files_from_authorized_oss_shrink_request.py
alibabacloud_bailian20231229/models/_apply_file_upload_lease_request.py
alibabacloud_bailian20231229/models/_apply_file_upload_lease_response.py
alibabacloud_bailian20231229/models/_apply_file_upload_lease_response_body.py
alibabacloud_bailian20231229/models/_apply_temp_storage_lease_request.py
alibabacloud_bailian20231229/models/_apply_temp_storage_lease_response.py
alibabacloud_bailian20231229/models/_apply_temp_storage_lease_response_body.py
alibabacloud_bailian20231229/models/_change_parse_setting_request.py
alibabacloud_bailian20231229/models/_change_parse_setting_response.py
alibabacloud_bailian20231229/models/_change_parse_setting_response_body.py
alibabacloud_bailian20231229/models/_change_parse_setting_shrink_request.py
alibabacloud_bailian20231229/models/_create_and_pulish_agent_request.py
alibabacloud_bailian20231229/models/_create_and_pulish_agent_response.py
alibabacloud_bailian20231229/models/_create_and_pulish_agent_response_body.py
alibabacloud_bailian20231229/models/_create_and_pulish_agent_shrink_request.py
alibabacloud_bailian20231229/models/_create_index_request.py
alibabacloud_bailian20231229-2.8.0.dist-info/LICENSE
alibabacloud_bailian20231229-2.8.0.dist-info/METADATA
alibabacloud_bailian20231229-2.8.0.dist-info/WHEEL
alibabacloud_bailian20231229-2.8.0.dist-info/top_level.txt
alibabacloud_bailian20231229-2.8.0.dist-info/RECORD
